realtime_pipeline/__init__.py
realtime_pipeline/manager/progress.py
realtime_pipeline/realtime_pipeline.py
realtime_pipeline/utils/typings.py
realtime_pipeline-0.5.3.dist-info/licenses/LICENSE
realtime_pipeline-0.5.3.dist-info/WHEEL
realtime_pipeline-0.5.3.dist-info/METADATA
realtime_pipeline-0.5.3.dist-info/RECORD
